{
  "@context": "http://purl.imsglobal.org/ctx/caliper/v1p2",
  "id": null,
  "type": "Person",
  "otherIdentifiers": [
    {
      "type": "SystemIdentifier",
      "identifier": "example.edu:71ee7e42-f6d2-414a-80db-b69ac2defd4",
      "identifierType": "LisSourcedId"
    },
    {
      "type": "SystemIdentifier",
      "identifier": "https://example.edu/users/554433",
      "identifierType": "LtiUserId",
      "source":  {
        "id": "https://example.edu",
        "type": "SoftwareApplication"
      }
    },
    {
      "type": "SystemIdentifier",
      "identifier": "jane@example.edu",
      "identifierType": "EmailAddress",
      "source": "https://example.edu"
    }
  ],
  "dateCreated": "2016-08-01T06:00:00.000Z",
  "dateModified": "2016-09-02T11:30:00.000Z"
}
